devconf/__init__.py
devconf/flask_app.py
devconf-0.1.dist-info/METADATA
devconf-0.1.dist-info/RECORD
devconf-0.1.dist-info/WHEEL
devconf-0.1.dist-info/top_level.txt
